Metadata-Version: 2.1
Name: flake8-kw-args
Version: 0.0.3
Summary: Flake8 plugin to check explicitly passed arguments.
Home-page: https://github.com/casafari/flake8-kw-args
Author: Casafari
Author-email: tools@casafari.net
License: UNKNOWN
Platform: UNKNOWN
Classifier: Operating System :: OS Independent
Classifier: Programming Language :: Python :: 3.7
